MANIFEST.in
README.rst
requirements.txt
setup.py
lisa/__init__.py
lisa/client/ConfigManager.py
lisa/client/__init__.py
lisa/client/service.py
lisa/client/tap.py
lisa/client/configuration/lisa.json.sample
lisa/client/lang/getstrings.sh
lisa/client/lang/lisa.pot
lisa/client/lang/es/LC_MESSAGES/lisa.po
lisa/client/lang/fr/LC_MESSAGES/lisa.mo
lisa/client/lang/fr/LC_MESSAGES/lisa.po
lisa/client/lang/sv/LC_MESSAGES/lisa.po
lisa/client/lang/tr/LC_MESSAGES/lisa.po
lisa/client/lib/__init__.py
lisa/client/lib/listener.py
lisa/client/lib/player.py
lisa/client/lib/recorder.py
lisa/client/lib/speaker.py
lisa/client/lib/pocketsphinx/lisa.dic
lisa/client/lib/pocketsphinx/lisa.lm
lisa/client/sounds/pi-cancel.2.wav
lisa/client/sounds/pi-cancel.wav
lisa/client/sounds/pi-listening.2.wav
lisa/client/sounds/pi-listening.wav
lisa/client/sounds/pi-response.2.wav
lisa/client/sounds/pi-response.wav
lisa/client/test/__init__.py
lisa/client/test/test_sendmessage.py
lisa_client.egg-info/PKG-INFO
lisa_client.egg-info/SOURCES.txt
lisa_client.egg-info/dependency_links.txt
lisa_client.egg-info/namespace_packages.txt
lisa_client.egg-info/requires.txt
lisa_client.egg-info/top_level.txt
twisted/plugins/dropin.cache
twisted/plugins/lisaclient_plugin.py
twisted/plugins/lisaclient_plugin.pyc